{"songs":[{"title":"You’re the Best Thing About Me","artist":"U2"},{"title":"Agnes","artist":"Glass Animals"},{"title":"Up All Night","artist":"Beck"},{"title":"I Miss Those Days","artist":"Bleachers"},{"title":"Come Together","artist":"Gary Clark Jr. & Junkie XL"},{"title":"The Gold","artist":"Manchester Orchestra"},{"title":"Weekends","artist":"Amy Shark"},{"title":"All My Life","artist":"Honors"},{"title":"Two High","artist":"Moon Taxi"},{"title":"The Man","artist":"The Killers"},{"title":"DREAM","artist":"BISHOP BRIGGS"},{"title":"Sober Up","artist":"AJR"},{"title":"Vacation","artist":"Dirty Heads"},{"title":"Holy Mountain","artist":"Noel Gallagher's High Flying Birds"},{"title":"Can I Sit Next to You","artist":"Spoon"},{"title":"7","artist":"CATFISH AND THE BOTTLEMAN"},{"title":"Thunder","artist":"Imagine Dragons"},{"title":"Never There","artist":"Cake"},{"title":"No Roots","artist":"Alice Merton"},{"title":"The Night We Met","artist":"Lord Huron"},{"title":"Down","artist":"311"},{"title":"Whole Wide World","artist":"Cage the Elephant"},{"title":"May I Have This Dance (Remix) [feat. Chance the Rapper]","artist":"Francis and the Lights"},{"title":"Machinehead","artist":"Bush"},{"title":"THE WANTING","artist":"J RODDY WASTON AND THE BUSINESS"}]}